nohedidnt_py/__init__.py
nohedidnt_py/base.py
nohedidnt_py/common/__init__.py
nohedidnt_py/common/aliases.py
nohedidnt_py/common/enums.py
nohedidnt_py/common/imports.py
nohedidnt_py/common/utils.py
nohedidnt_py/constants.py
nohedidnt_py/helpers.py
nohedidnt_py-0.1.1.dist-info/LICENSE
nohedidnt_py-0.1.1.dist-info/WHEEL
nohedidnt_py-0.1.1.dist-info/METADATA
nohedidnt_py-0.1.1.dist-info/RECORD
